tests.py
logging_config/__init__.py
logging_config/middleware.py
dragonfly_logging_config-1.3.0.dist-info/LICENSE
dragonfly_logging_config-1.3.0.dist-info/METADATA
dragonfly_logging_config-1.3.0.dist-info/WHEEL
dragonfly_logging_config-1.3.0.dist-info/top_level.txt
dragonfly_logging_config-1.3.0.dist-info/RECORD
