Metadata-Version: 2.1
Name: dragonfly-logging-config
Version: 1.3.0
Summary: Shared logging configuration for Dragonfly codebases
Author-email: Vipyr Security <support@vipyrsec.com>
License: MIT
Requires-Python: >=3.11
License-File: LICENSE
Requires-Dist: structlog >=24.1.0
Requires-Dist: fastapi-slim >=0.110.0
Requires-Dist: asgi-correlation-id >=4.3.1
